writhe_tools/__init__.py
writhe_tools/md_tools.py
writhe_tools/msm_tools.py
writhe_tools/plots.py
writhe_tools/stats.py
writhe_tools/tcca.py
writhe_tools/writhe.py
writhe_tools/writhe_nn.py
writhe_tools/writhe_numba.py
writhe_tools/writhe_ray.py
writhe_tools/utils/__init__.py
writhe_tools/utils/filing.py
writhe_tools/utils/graph_utils.py
writhe_tools/utils/indexing.py
writhe_tools/utils/misc.py
writhe_tools/utils/sorting.py
writhe_tools/utils/torch_utils.py
writhe_tools-0.0.23.dist-info/licenses/LICENSE
writhe_tools-0.0.23.dist-info/METADATA
writhe_tools-0.0.23.dist-info/WHEEL
writhe_tools-0.0.23.dist-info/top_level.txt
writhe_tools-0.0.23.dist-info/RECORD
