Metadata-Version: 2.4
Name: writhe_tools
Version: 0.0.23
Summary: A high-performance Python package for computing the geometric descriptor writhe from 3D coordinate data.
Home-page: 
Author: Thomas Sisk
Author-email: Thomas Sisk <Thomas.r.Sisk.gr@dartmouth.edu>
License: GPL-3.0-only
Project-URL: Homepage, https://github.com/tommysisk/writhe_tools
Requires-Python: >=3.7, <3.11
License-File: LICENSE
Requires-Dist: numpy<2.0,>=1.22.4
Requires-Dist: ray>=2.5.1
Requires-Dist: matplotlib>=3.5.1
Requires-Dist: torch>=2.0.1
Requires-Dist: numpy_indexed>=0.3.7
Requires-Dist: joblib>=1.1.0
Requires-Dist: numba>=0.55.0
Provides-Extra: cuda11
Requires-Dist: numpy<2.0,>=1.22.4; extra == "cuda11"
Requires-Dist: ray<3.0,>=2.5.1; extra == "cuda11"
Requires-Dist: matplotlib<4.0,>=3.5.1; extra == "cuda11"
Requires-Dist: torch<2.1.0,>=2.0.1; extra == "cuda11"
Requires-Dist: numpy_indexed<1.0,>=0.3.7; extra == "cuda11"
Requires-Dist: joblib<2.0,>=1.1.0; extra == "cuda11"
Requires-Dist: numba<0.61.0,>=0.55.0; extra == "cuda11"
Provides-Extra: cuda11-graph
Requires-Dist: numpy<2.0,>=1.22.4; extra == "cuda11-graph"
Requires-Dist: ray<3.0,>=2.5.1; extra == "cuda11-graph"
Requires-Dist: matplotlib<4.0,>=3.5.1; extra == "cuda11-graph"
Requires-Dist: torch<2.1.0,>=2.0.1; extra == "cuda11-graph"
Requires-Dist: numpy_indexed<1.0,>=0.3.7; extra == "cuda11-graph"
Requires-Dist: joblib<2.0,>=1.1.0; extra == "cuda11-graph"
Requires-Dist: numba<0.61.0,>=0.55.0; extra == "cuda11-graph"
Requires-Dist: tqdm<5.0,>=4.63.0; extra == "cuda11-graph"
Requires-Dist: pytorch_lightning<=2.0.9.post0; extra == "cuda11-graph"
Requires-Dist: torch-geometric<3.0,>=2.3.1; extra == "cuda11-graph"
Requires-Dist: tensorboard<3.0,>=2.13.0; extra == "cuda11-graph"
Provides-Extra: graph
Requires-Dist: torch-geometric<3.0,>=2.3.1; extra == "graph"
Requires-Dist: tensorboard<3.0,>=2.13.0; extra == "graph"
Requires-Dist: torch-scatter<3.0,>=2.1.1; extra == "graph"
Requires-Dist: pytorch_lightning<3.0,>=2.0.9.post0; extra == "graph"
Requires-Dist: tqdm<5.0,>=4.63.0; extra == "graph"
Provides-Extra: mdtraj
Requires-Dist: mdtraj<2.0,>=1.9.5; extra == "mdtraj"
Provides-Extra: stats
Requires-Dist: dask>=2022.2.1; extra == "stats"
Requires-Dist: deeptime>=0.4.1; extra == "stats"
Requires-Dist: scipy>=1.9.0; extra == "stats"
Requires-Dist: scikit-learn>=1.5.0; extra == "stats"
Provides-Extra: dev
Requires-Dist: pytest<8.0.0,>=6.0.0; extra == "dev"
Requires-Dist: black<24.0.0,>=22.0.0; extra == "dev"
Requires-Dist: flake8<6.0.0,>=4.0.0; extra == "dev"
Dynamic: author
Dynamic: license-file
Dynamic: requires-python
